paginator/__init__.py
paginator/core.py
paginator/utils.py
paginator/__pycache__/__init__.cpython-39.pyc
paginator/__pycache__/core.cpython-39.pyc
paginator/__pycache__/utils.cpython-39.pyc
paginator/tests/__init__.py
paginator/tests/test_paginator.py
paginator/tests/__pycache__/__init__.cpython-39.pyc
paginator/tests/__pycache__/test_paginator.cpython-39-pytest-7.1.2.pyc
python_paginator-0.0.2.dist-info/LICENSE.txt
python_paginator-0.0.2.dist-info/METADATA
python_paginator-0.0.2.dist-info/WHEEL
python_paginator-0.0.2.dist-info/top_level.txt
python_paginator-0.0.2.dist-info/RECORD
