Metadata-Version: 2.1
Name: python-paginator
Version: 0.0.2
Summary: Python object paginator
Home-page: UNKNOWN
Author: Patryk Dąbrowski
Author-email: tibiasportex@gmail.com
License: UNKNOWN
Keywords: python,paginator
Platform: UNKNOWN
Classifier: Development Status :: 3 - Alpha
Classifier: Intended Audience :: Education
Classifier: Programming Language :: Python :: 3
Classifier: License :: OSI Approved :: MIT License
Classifier: Operating System :: OS Independent
License-File: LICENSE.txt
Requires-Dist: pydantic
